AUTHORS.md
LICENSE
README.rst
pyproject.toml
setup.py
docs/source/conf.py
pytim/__init__.py
pytim/atoms_maps.py
pytim/circumradius.pyx
pytim/cube.py
pytim/dbscan_inner.pyx
pytim/gaussian_kde_pbc.py
pytim/gitim.py
pytim/interface.py
pytim/itim.py
pytim/messages.py
pytim/patches.py
pytim/properties.py
pytim/sanity_check.py
pytim/sasa.py
pytim/simple_interface.py
pytim/surface.py
pytim/utilities.py
pytim/utilities_dbscan.py
pytim/utilities_geometry.py
pytim/utilities_mesh.py
pytim/utilities_pbc.py
pytim/version.py
pytim/vtk.py
pytim/wavefront_obj.py
pytim/willard_chandler.py
pytim/writepdb.py
pytim.egg-info/PKG-INFO
pytim.egg-info/SOURCES.txt
pytim.egg-info/dependency_links.txt
pytim.egg-info/requires.txt
pytim.egg-info/top_level.txt
pytim/data/CCL4.H2O.GRO
pytim/data/LJ.gro
pytim/data/LJ.short.xtc
pytim/data/_test_bcc.gro
pytim/data/_test_orientation.gro
pytim/data/_test_profile.gro
pytim/data/antagonistic.gro
pytim/data/dppc.gro
pytim/data/ffamber03.nonbonded.itp
pytim/data/ffcharmm27.nonbonded.itp
pytim/data/ffg43a1.nonbonded.itp
pytim/data/fullerene.pdb
pytim/data/glucose.pdb
pytim/data/ilbenzene.gro
pytim/data/logo.pdf
pytim/data/logo.svg
pytim/data/methanol.gro
pytim/data/micelle.pdb
pytim/data/water-2-interfaces.gro
pytim/data/water-small.gro
pytim/data/water.gro
pytim/data/water.pdb
pytim/data/water.xtc
pytim/data/water.xyz
pytim/data/water_520K.gro
pytim/data/water_550K.gro
pytim/data/water_droplet_cylindrical.gro
pytim/data/water_droplet_cylindrical.xtc
pytim/data/water_droplet_spherical.gro
pytim/data/water_lmp.data
pytim/data/water_lmp.xtc
pytim/datafiles/__init__.py
pytim/examples/example_gitim_flat.py
pytim/examples/example_mdtraj.py
pytim/examples/example_micelle.py
pytim/examples/example_openmm.py
pytim/examples/example_profile.py
pytim/examples/example_rdf.py
pytim/examples/example_triangulation.py
pytim/examples/example_water-molecular-layer.py
pytim/examples/example_water.py
pytim/examples/example_willard_chandler.py
pytim/observables/__init__.py
pytim/observables/adjacency_matrix.py
pytim/observables/basic_observables.py
pytim/observables/contactangle.py
pytim/observables/correlator.py
